frost_sta_client/__init__.py
frost_sta_client/__version__.py
frost_sta_client/utils.py
frost_sta_client/dao/__init__.py
frost_sta_client/dao/actuator.py
frost_sta_client/dao/base.py
frost_sta_client/dao/datastream.py
frost_sta_client/dao/features_of_interest.py
frost_sta_client/dao/historical_location.py
frost_sta_client/dao/location.py
frost_sta_client/dao/multi_datastream.py
frost_sta_client/dao/observation.py
frost_sta_client/dao/observedproperty.py
frost_sta_client/dao/sensor.py
frost_sta_client/dao/task.py
frost_sta_client/dao/tasking_capability.py
frost_sta_client/dao/thing.py
frost_sta_client/model/__init__.py
frost_sta_client/model/actuator.py
frost_sta_client/model/datastream.py
frost_sta_client/model/entity.py
frost_sta_client/model/feature_of_interest.py
frost_sta_client/model/historical_location.py
frost_sta_client/model/location.py
frost_sta_client/model/multi_datastream.py
frost_sta_client/model/observation.py
frost_sta_client/model/observedproperty.py
frost_sta_client/model/sensor.py
frost_sta_client/model/task.py
frost_sta_client/model/tasking_capability.py
frost_sta_client/model/thing.py
frost_sta_client/model/ext/__init__.py
frost_sta_client/model/ext/data_array_document.py
frost_sta_client/model/ext/data_array_value.py
frost_sta_client/model/ext/entity_list.py
frost_sta_client/model/ext/entity_type.py
frost_sta_client/model/ext/unitofmeasurement.py
frost_sta_client/query/__init__.py
frost_sta_client/query/query.py
frost_sta_client/service/__init__.py
frost_sta_client/service/auth_handler.py
frost_sta_client/service/sensorthingsservice.py
sd_frost_sta_client-1.1.45.dist-info/LICENSE
sd_frost_sta_client-1.1.45.dist-info/METADATA
sd_frost_sta_client-1.1.45.dist-info/WHEEL
sd_frost_sta_client-1.1.45.dist-info/top_level.txt
sd_frost_sta_client-1.1.45.dist-info/RECORD
