Metadata-Version: 2.1
Name: sd-frost-sta-client
Version: 1.1.45
Summary: An improved version of the client library originally developed by Fraunhofer to facilitate interaction with a SensorThings API v1.1 Server
Home-page: https://github.com/securedimensions/STA-Python-Client
Author: Andreas Matheus
Author-email: andreas.matheus@secure-dimensions.de
License: LGPL3
Keywords: sta,ogc,frost,sensorthingsapi,IoT
License-File: LICENSE
Requires-Dist: demjson3 >=3.0.5
Requires-Dist: furl >=2.1.3
Requires-Dist: geojson >=2.5.0
Requires-Dist: jsonpickle >=2.0.0
Requires-Dist: requests >=2.26.0
Requires-Dist: jsonpatch
Requires-Dist: python-dateutil
